{
  "n_works": 21203,
  "n_authorships": 205638,
  "n_unique_authors": 84482,
  "n_countries": 202,
  "median_team_size": 7,
  "iqr_team_size_lo": 4,
  "iqr_team_size_hi": 11,
  "mean_team_size": 9.7,
  "year_range": "2000-2025",
  "pct_articles": 78.6,
  "pct_reviews": 8.9,
  "pct_preprints": 8.0,
  "pct_oa": 77.1,
  "pct_funded": 41.0,
  "fwci_median": 1.16,
  "fwci_iqr_lo": 0.18,
  "fwci_iqr_hi": 3.12,
  "fwci_missing_pct": 8.8,
  "mk_first_trend": "no trend",
  "mk_first_tau": -0.071,
  "mk_first_p": 0.6277,
  "mk_last_trend": "no trend",
  "mk_last_tau": 0.052,
  "mk_last_p": 0.7243,
  "mk_bilateral_trend": "increasing",
  "mk_bilateral_tau": 0.434,
  "mk_bilateral_p": 0.002,
  "mk_multibloc_trend": "no trend",
  "mk_multibloc_tau": -0.04,
  "mk_multibloc_p": 0.7914,
  "first_is_corr_pct": 78.2
}